{"_type":"export","__export_format":4,"__export_date":"2019-08-21T01:00:36.219Z","__export_source":"insomnia.desktop.app:v6.6.2","resources":[{"_id":"req_69e3069cdb2c486bb7c51ee8908ad2d0","authentication":{},"body":{"mimeType":"application/json","text":"{\n\t\"email\": \"brochj@gmail.com\",\n\t\"password\": \"123456\"\n}"},"created":1566329856465,"description":"","headers":[{"id":"pair_2df0cfb3e4dc469795dcc3cdd5f31a61","name":"Content-Type","value":"application/json"}],"isPrivate":false,"metaSortKey":-1566286903519,"method":"POST","modified":1566345024985,"name":"Create","parameters":[],"parentId":"fld_ed67c749879b4a10a6e2b64f044c7256","settingDisableRenderRequestBody":false,"settingEncodeUrl":true,"settingRebuildPath":true,"settingSendCookies":true,"settingStoreCookies":true,"url":"{{ base_url  }}/sessions","_type":"request"},{"_id":"fld_ed67c749879b4a10a6e2b64f044c7256","created":1566329844984,"description":"","environment":{},"environmentPropertyOrder":null,"metaSortKey":-1566329844984,"modified":1566329844984,"name":"Sessions","parentId":"wrk_65a8382c363644f78b9300f354f96034","_type":"request_group"},{"_id":"wrk_65a8382c363644f78b9300f354f96034","created":1566323608548,"description":"","modified":1566323608548,"name":"goBarber","parentId":null,"_type":"workspace"},{"_id":"req_dd86170bf48d4e6597ebf0e796fa360f","authentication":{},"body":{"mimeType":"application/json","text":"{\n\t\"name\": \"Oscar broch\",\n\t\"email\": \"brochj@gmail.com\",\n\t\"password\": \"123456\"\n}"},"created":1566323690334,"description":"","headers":[{"id":"pair_2df0cfb3e4dc469795dcc3cdd5f31a61","name":"Content-Type","value":"application/json"}],"isPrivate":false,"metaSortKey":-1566323690335,"method":"POST","modified":1566344999830,"name":"Create","parameters":[],"parentId":"fld_7fc79fd927144cbf9d97f22de24b22f2","settingDisableRenderRequestBody":false,"settingEncodeUrl":true,"settingRebuildPath":true,"settingSendCookies":true,"settingStoreCookies":true,"url":"{{ base_url  }}/users","_type":"request"},{"_id":"fld_7fc79fd927144cbf9d97f22de24b22f2","created":1566323620876,"description":"","environment":{},"environmentPropertyOrder":null,"metaSortKey":-1566323620876,"modified":1566323620876,"name":"Users","parentId":"wrk_65a8382c363644f78b9300f354f96034","_type":"request_group"},{"_id":"req_e11cd05fe789466d8ae9d0447b7d133f","authentication":{"token":"eyJhbGciOiJIUzI1NiIsInR5cCI6IkpXVCJ9.eyJpZCI6MTAsImlhdCI6MTU2NjM0NTAyNiwiZXhwIjoxNTY2OTQ5ODI2fQ.bWSj27yeMYqIb0MLCE_oGKqoIE2LF62FTBp2yjAk4hs","type":"bearer"},"body":{"mimeType":"application/json","text":"{\n\t\"name\": \"Oscar Broch Junior\",\n\t\"email\": \"brochj@gmail.com\",\n\t\"oldPassword\": \"12345678\",\n\t\"password\": \"123456\",\n\t\"confirmPassword\":\"123456\"\n}"},"created":1566331425775,"description":"","headers":[{"id":"pair_2df0cfb3e4dc469795dcc3cdd5f31a61","name":"Content-Type","value":"application/json"}],"isPrivate":false,"metaSortKey":-1566305296927,"method":"PUT","modified":1566345131752,"name":"Update","parameters":[],"parentId":"fld_7fc79fd927144cbf9d97f22de24b22f2","settingDisableRenderRequestBody":false,"settingEncodeUrl":true,"settingRebuildPath":true,"settingSendCookies":true,"settingStoreCookies":true,"url":"{{ base_url  }}/users","_type":"request"},{"_id":"env_da2d9000c194e46fabc8f9d23a11f33208f497c8","color":null,"created":1566323608634,"data":{"base_url":"http://localhost:3333"},"dataPropertyOrder":{"&":["base_url"]},"isPrivate":false,"metaSortKey":1566323608634,"modified":1566323657680,"name":"Base Environment","parentId":"wrk_65a8382c363644f78b9300f354f96034","_type":"environment"},{"_id":"jar_da2d9000c194e46fabc8f9d23a11f33208f497c8","cookies":[],"created":1566323608639,"modified":1566323608639,"name":"Default Jar","parentId":"wrk_65a8382c363644f78b9300f354f96034","_type":"cookie_jar"}]}